faker_datasets/__init__.py
faker_datasets-0.1.0.dist-info/LICENSE
faker_datasets-0.1.0.dist-info/METADATA
faker_datasets-0.1.0.dist-info/WHEEL
faker_datasets-0.1.0.dist-info/top_level.txt
faker_datasets-0.1.0.dist-info/RECORD
