Metadata-Version: 2.1
Name: faker-datasets
Version: 0.1.0
Summary: Faker provider that loads data from your datasets
Author-email: Domenico Andreoli <domenico.andreoli@elastic.co>
License: Copyright (c) 2022 Elasticsearch B.V.
Project-URL: Homepage, https://github.com/elastic/faker-datasets
Project-URL: Bug Tracker, https://github.com/elastic/faker-datasets/issues
Keywords: faker,fixtures,data,test,mock,generator
Classifier: License :: OSI Approved :: MIT License
Classifier: Programming Language :: Python
Classifier: Topic :: Software Development :: Libraries :: Python Modules
Classifier: Topic :: Software Development :: Quality Assurance
Classifier: Topic :: Software Development :: Testing
Requires-Python: >=3.8
License-File: LICENSE
Requires-Dist: faker
